quickprophet/__init__.py
quickprophet/features.py
quickprophet/impute.py
quickprophet/models.py
quickprophet-0.0.17.dist-info/METADATA
quickprophet-0.0.17.dist-info/WHEEL
quickprophet-0.0.17.dist-info/licenses/LICENSE
quickprophet-0.0.17.dist-info/RECORD
